LICENSE
epub3/__init__.py
epub3/__main__.py
epub3/epub.py
epub3/extension/__init__.py
epub3/extension/pack.py
epub3/util/__init__.py
epub3/util/_init_mimetypes.py
epub3/util/file.py
epub3/util/helper.py
epub3/util/proxy.py
epub3/util/remap.py
epub3/util/stream.py
epub3/util/template.py
epub3/util/undefined.py
epub3/util/xml.py
epub3/util/xml_plus.py
python_epub3-0.0.1.15.dist-info/LICENSE
python_epub3-0.0.1.15.dist-info/METADATA
python_epub3-0.0.1.15.dist-info/WHEEL
python_epub3-0.0.1.15.dist-info/RECORD
